minimum_pipeline/FilterAndClear.py
minimum_pipeline/__init__.py
minimum_pipeline/cli.py
minimum_pipeline/extract.py
minimum_pipeline/pipeline.py
minimum_pipeline/types.py
minimum_pipeline-1.2.1.dist-info/METADATA
minimum_pipeline-1.2.1.dist-info/WHEEL
minimum_pipeline-1.2.1.dist-info/entry_points.txt
minimum_pipeline-1.2.1.dist-info/top_level.txt
minimum_pipeline-1.2.1.dist-info/RECORD
