Metadata-Version: 2.4
Name: minimum-pipeline
Version: 1.2.1
Summary: Data pipeline: extract → classify → clean → split.
Author: Daniel Valdez
License: MIT
Requires-Python: >=3.10
Requires-Dist: pandas>=2.3.1
Requires-Dist: numpy>=2.1
Requires-Dist: scikit-learn>=1.7.1
